README.md
setup.py
gitalizer/__init__.py
gitalizer.egg-info/PKG-INFO
gitalizer.egg-info/SOURCES.txt
gitalizer.egg-info/dependency_links.txt
gitalizer.egg-info/entry_points.txt
gitalizer.egg-info/requires.txt
gitalizer.egg-info/top_level.txt
gitalizer/aggregator/__init__.py
gitalizer/aggregator/git/__init__.py
gitalizer/aggregator/git/commit.py
gitalizer/aggregator/git/repository.py
gitalizer/aggregator/github/__init__.py
gitalizer/aggregator/github/organization.py
gitalizer/aggregator/github/repository.py
gitalizer/aggregator/github/user.py
gitalizer/cli/__init__.py
gitalizer/cli/db.py
gitalizer/cli/delete.py
gitalizer/cli/maintenance.py
gitalizer/cli/organization.py
gitalizer/cli/repository.py
gitalizer/cli/user.py
gitalizer/extensions/__init__.py
gitalizer/extensions/github.py
gitalizer/extensions/logger.py
gitalizer/extensions/sentry.py
gitalizer/extensions/sqlalchemy.py
gitalizer/helpers/__init__.py
gitalizer/helpers/config.py
gitalizer/helpers/db/__init__.py
gitalizer/helpers/db/maintenance.py
gitalizer/helpers/parallel/__init__.py
gitalizer/helpers/parallel/list_manager.py
gitalizer/helpers/parallel/manager.py
gitalizer/helpers/parallel/messages.py
gitalizer/helpers/parallel/task.py
gitalizer/helpers/parallel/worker.py
gitalizer/models/__init__.py
gitalizer/models/analysis_result.py
gitalizer/models/commit.py
gitalizer/models/contributor.py
gitalizer/models/email.py
gitalizer/models/organization.py
gitalizer/models/repository.py
gitalizer/models/time.py
gitalizer/timezone/__init__.py
gitalizer/timezone/database.py